{
    "js1":"Tìm tên phim",
    "js2":"Đắng Nhập",
    "js3":"MUA VÉ",
    "js4":"PHIM",
    "js5":"GÓC ĐIỆN ẢNH",
    "js6":"SỰ KIỆN",
    "js7":"RẠP/GIÁ VÉ",
    "js8":"HỖ TRỢ",
    "js9":"THÀNH VIÊN",
    "js10":"PHIM ĐANG CHIẾU",
    "js11":"PHIM SẮP CHIẾU",
    "js12":"Terminator: Dark Fate hứa hẹn là phần phim chắc chắn sẽ khiến các fan hâm mộ thỏa mãn bởi ..",
    "js13":"Phim kể về một cặp anh em với sở thích ngồi ngoài đồng cùng hát bài dân ca Bắc Kim Thang ..",
    "js14":"Phim kể về một cặp anh em với sở thích ngồi ngoài đồng cùng hát bài dân ca Bắc Kim Thang ..",
    "js15":"Xem thêm"
}